{
"meta":{"test_sets":[],"test_metrics":[],"learn_metrics":[{"best_value":"Min","name":"Logloss"}],"launch_mode":"Train","parameters":"","iteration_count":700,"learn_sets":["learn"],"name":"experiment"},
"iterations":[
{"learn":[0.6689899286],"iteration":0,"passed_time":0.01897194164,"remaining_time":13.2613872},
{"learn":[0.6497871083],"iteration":1,"passed_time":0.03439001755,"remaining_time":12.00211612},
{"learn":[0.6341304441],"iteration":2,"passed_time":0.05030891862,"remaining_time":11.68843876},
{"learn":[0.6220606142],"iteration":3,"passed_time":0.06749818437,"remaining_time":11.74468408},
{"learn":[0.6118303923],"iteration":4,"passed_time":0.08475484146,"remaining_time":11.78092296},
{"learn":[0.6038812749],"iteration":5,"passed_time":0.101948329,"remaining_time":11.79202339},
{"learn":[0.5959388822],"iteration":6,"passed_time":0.1192517548,"remaining_time":11.80592373},
{"learn":[0.589985382],"iteration":7,"passed_time":0.1363908558,"remaining_time":11.79780903},
{"learn":[0.5851670664],"iteration":8,"passed_time":0.1535781064,"remaining_time":11.79138573},
{"learn":[0.580469042],"iteration":9,"passed_time":0.1697457214,"remaining_time":11.71245478},
{"learn":[0.5769069458],"iteration":10,"passed_time":0.1869471864,"remaining_time":11.70969195},
{"learn":[0.5735355849],"iteration":11,"passed_time":0.204754747,"remaining_time":11.73927216},
{"learn":[0.5710512081],"iteration":12,"passed_time":0.2212267313,"remaining_time":11.69098188},
{"learn":[0.5687793529],"iteration":13,"passed_time":0.2371952829,"remaining_time":11.62256886},
{"learn":[0.5668306791],"iteration":14,"passed_time":0.2541234385,"remaining_time":11.60497036},
{"learn":[0.56508514],"iteration":15,"passed_time":0.2712645356,"remaining_time":11.5965589},
{"learn":[0.5635659746],"iteration":16,"passed_time":0.2882135299,"remaining_time":11.57940241},
{"learn":[0.5622695921],"iteration":17,"passed_time":0.3060181354,"remaining_time":11.59468713},
{"learn":[0.56088207],"iteration":18,"passed_time":0.3241765414,"remaining_time":11.61916972},
{"learn":[0.5600944383],"iteration":19,"passed_time":0.3419840279,"remaining_time":11.62745695},
{"learn":[0.5591413738],"iteration":20,"passed_time":0.358796255,"remaining_time":11.60107891},
{"learn":[0.5582007253],"iteration":21,"passed_time":0.3768848264,"remaining_time":11.6149051},
{"learn":[0.5573242821],"iteration":22,"passed_time":0.3940999589,"remaining_time":11.60024662},
{"learn":[0.5566329098],"iteration":23,"passed_time":0.4109070643,"remaining_time":11.57388231},
{"learn":[0.5560016501],"iteration":24,"passed_time":0.4287812219,"remaining_time":11.57709299},
{"learn":[0.5553512966],"iteration":25,"passed_time":0.4456744188,"remaining_time":11.55325224},
{"learn":[0.5547975241],"iteration":26,"passed_time":0.461887472,"remaining_time":11.51297291},
{"learn":[0.5542066155],"iteration":27,"passed_time":0.4782892671,"remaining_time":11.47894241},
{"learn":[0.5537798401],"iteration":28,"passed_time":0.4941687088,"remaining_time":11.4340415},
{"learn":[0.5534386689],"iteration":29,"passed_time":0.510597055,"remaining_time":11.40333423},
{"learn":[0.5530034499],"iteration":30,"passed_time":0.5268086627,"remaining_time":11.36887082},
{"learn":[0.5526240827],"iteration":31,"passed_time":0.542860105,"remaining_time":11.33220469},
{"learn":[0.5523112952],"iteration":32,"passed_time":0.5604728298,"remaining_time":11.32834477},
{"learn":[0.5519631646],"iteration":33,"passed_time":0.5776976549,"remaining_time":11.31607759},
{"learn":[0.5516668126],"iteration":34,"passed_time":0.5949209515,"remaining_time":11.30349808},
{"learn":[0.5514048854],"iteration":35,"passed_time":0.6128448278,"remaining_time":11.30358238},
{"learn":[0.5512384795],"iteration":36,"passed_time":0.6301524142,"remaining_time":11.29165002},
{"learn":[0.5509782791],"iteration":37,"passed_time":0.6464692724,"remaining_time":11.26217522},
{"learn":[0.5507018101],"iteration":38,"passed_time":0.6629336649,"remaining_time":11.2358757},
{"learn":[0.5504285363],"iteration":39,"passed_time":0.6810400284,"remaining_time":11.23716047},
{"learn":[0.5501931829],"iteration":40,"passed_time":0.6979349807,"remaining_time":11.2180281},
{"learn":[0.5500515655],"iteration":41,"passed_time":0.71673022,"remaining_time":11.22877345},
{"learn":[0.5496731416],"iteration":42,"passed_time":0.7331885571,"remaining_time":11.20243912},
{"learn":[0.5494590145],"iteration":43,"passed_time":0.7510773941,"remaining_time":11.19788115},
{"learn":[0.5492996462],"iteration":44,"passed_time":0.7686799004,"remaining_time":11.18856299},
{"learn":[0.5491388339],"iteration":45,"passed_time":0.7864767907,"remaining_time":11.18164829},
{"learn":[0.5490314164],"iteration":46,"passed_time":0.804521067,"remaining_time":11.17770759},
{"learn":[0.5488070045],"iteration":47,"passed_time":0.8227116831,"remaining_time":11.17516703},
{"learn":[0.5486390427],"iteration":48,"passed_time":0.840560098,"remaining_time":11.1674413},
{"learn":[0.5484531551],"iteration":49,"passed_time":0.8604984036,"remaining_time":11.18647925},
{"learn":[0.5482915764],"iteration":50,"passed_time":0.890505058,"remaining_time":11.33211338},
{"learn":[0.5481691133],"iteration":51,"passed_time":0.9111726291,"remaining_time":11.35461276},
{"learn":[0.5480444329],"iteration":52,"passed_time":0.9315251124,"remaining_time":11.37163675},
{"learn":[0.5479347925],"iteration":53,"passed_time":0.950815327,"remaining_time":11.37456854},
{"learn":[0.5478446973],"iteration":54,"passed_time":0.9706152681,"remaining_time":11.38266996},
{"learn":[0.5477446099],"iteration":55,"passed_time":0.9909798252,"remaining_time":11.39626799},
{"learn":[0.5475749484],"iteration":56,"passed_time":1.010601004,"remaining_time":11.40028852},
{"learn":[0.5475200116],"iteration":57,"passed_time":1.030255206,"remaining_time":11.40385935},
{"learn":[0.5473905821],"iteration":58,"passed_time":1.049465809,"remaining_time":11.40182345},
{"learn":[0.5471869314],"iteration":59,"passed_time":1.068076764,"remaining_time":11.39281881},
{"learn":[0.5470801859],"iteration":60,"passed_time":1.087333286,"remaining_time":11.39026179},
{"learn":[0.5469868512],"iteration":61,"passed_time":1.106502439,"remaining_time":11.38626704},
{"learn":[0.5468852951],"iteration":62,"passed_time":1.12606702,"remaining_time":11.38578876},
{"learn":[0.5468329598],"iteration":63,"passed_time":1.147007151,"remaining_time":11.39838356},
{"learn":[0.5467650475],"iteration":64,"passed_time":1.166591511,"remaining_time":11.39670169},
{"learn":[0.5466477963],"iteration":65,"passed_time":1.185209024,"remaining_time":11.38518972},
{"learn":[0.5465344506],"iteration":66,"passed_time":1.206292635,"remaining_time":11.39676474},
{"learn":[0.5464822509],"iteration":67,"passed_time":1.224798413,"remaining_time":11.38342054},
{"learn":[0.5464262566],"iteration":68,"passed_time":1.244062312,"remaining_time":11.37685969},
{"learn":[0.5462636872],"iteration":69,"passed_time":1.263213222,"remaining_time":11.368919},
{"learn":[0.5461749707],"iteration":70,"passed_time":1.28200938,"remaining_time":11.35751972},
{"learn":[0.546104125],"iteration":71,"passed_time":1.301426002,"remaining_time":11.35132679},
{"learn":[0.5459850199],"iteration":72,"passed_time":1.320338231,"remaining_time":11.34043933},
{"learn":[0.5459335581],"iteration":73,"passed_time":1.338526031,"remaining_time":11.32320669},
{"learn":[0.5458971725],"iteration":74,"passed_time":1.356775902,"remaining_time":11.30646585},
{"learn":[0.5458210993],"iteration":75,"passed_time":1.376662239,"remaining_time":11.30312154},
{"learn":[0.5457173709],"iteration":76,"passed_time":1.394975842,"remaining_time":11.28662272},
{"learn":[0.545651487],"iteration":77,"passed_time":1.413071309,"remaining_time":11.26833787},
{"learn":[0.5455854247],"iteration":78,"passed_time":1.432631887,"remaining_time":11.26157471},
{"learn":[0.5455084301],"iteration":79,"passed_time":1.450353476,"remaining_time":11.24023944},
{"learn":[0.5454801743],"iteration":80,"passed_time":1.46845798,"remaining_time":11.22191962},
{"learn":[0.545453397],"iteration":81,"passed_time":1.487201209,"remaining_time":11.20841887},
{"learn":[0.5453873427],"iteration":82,"passed_time":1.504975715,"remaining_time":11.18759056},
{"learn":[0.5453536663],"iteration":83,"passed_time":1.523872479,"remaining_time":11.17506485},
{"learn":[0.5453130514],"iteration":84,"passed_time":1.542782776,"remaining_time":11.16248715},
{"learn":[0.5452360794],"iteration":85,"passed_time":1.561662759,"remaining_time":11.14954574},
{"learn":[0.5451860233],"iteration":86,"passed_time":1.581936348,"remaining_time":11.14628714},
{"learn":[0.5451387423],"iteration":87,"passed_time":1.601182712,"remaining_time":11.13549795},
{"learn":[0.5450613513],"iteration":88,"passed_time":1.619602993,"remaining_time":11.11884751},
{"learn":[0.5449694149],"iteration":89,"passed_time":1.638626823,"remaining_time":11.10624847},
{"learn":[0.5449124506],"iteration":90,"passed_time":1.658117196,"remaining_time":11.09663046},
{"learn":[0.5448741903],"iteration":91,"passed_time":1.676927361,"remaining_time":11.08230256},
{"learn":[0.5447984777],"iteration":92,"passed_time":1.695368332,"remaining_time":11.06546858},
{"learn":[0.5447323301],"iteration":93,"passed_time":1.714095254,"remaining_time":11.05044387},
{"learn":[0.5446601551],"iteration":94,"passed_time":1.732192522,"remaining_time":11.03133132},
{"learn":[0.5445903611],"iteration":95,"passed_time":1.749979755,"remaining_time":11.01028929},
{"learn":[0.5445545043],"iteration":96,"passed_time":1.767512054,"remaining_time":10.98772958},
{"learn":[0.5444908173],"iteration":97,"passed_time":1.785338527,"remaining_time":10.96707953},
{"learn":[0.5444418608],"iteration":98,"passed_time":1.803756796,"remaining_time":10.95007914},
{"learn":[0.5444002329],"iteration":99,"passed_time":1.822146616,"remaining_time":10.9328797},
{"learn":[0.5443178811],"iteration":100,"passed_time":1.839177483,"remaining_time":10.90759715},
{"learn":[0.5442800351],"iteration":101,"passed_time":1.857379609,"remaining_time":10.8893432},
{"learn":[0.5442447943],"iteration":102,"passed_time":1.875191459,"remaining_time":10.86882817},
{"learn":[0.5442233673],"iteration":103,"passed_time":1.893463414,"remaining_time":10.85100187},
{"learn":[0.5441622716],"iteration":104,"passed_time":1.911787728,"remaining_time":10.83346379},
{"learn":[0.5441293908],"iteration":105,"passed_time":1.929081383,"remaining_time":10.81013529},
{"learn":[0.5441104949],"iteration":106,"passed_time":1.945973036,"remaining_time":10.78469169},
{"learn":[0.5440475334],"iteration":107,"passed_time":1.963939587,"remaining_time":10.76529848},
{"learn":[0.5439994405],"iteration":108,"passed_time":1.982262888,"remaining_time":10.74786575},
{"learn":[0.5439299475],"iteration":109,"passed_time":1.999764335,"remaining_time":10.72600871},
{"learn":[0.5438506445],"iteration":110,"passed_time":2.017297455,"remaining_time":10.70439821},
{"learn":[0.5438037133],"iteration":111,"passed_time":2.034574362,"remaining_time":10.6815154},
{"learn":[0.5437651249],"iteration":112,"passed_time":2.051140155,"remaining_time":10.6550378},
{"learn":[0.5437339615],"iteration":113,"passed_time":2.067313968,"remaining_time":10.62671917},
{"learn":[0.5436899025],"iteration":114,"passed_time":2.085073037,"remaining_time":10.60667589},
{"learn":[0.5436583992],"iteration":115,"passed_time":2.102571759,"remaining_time":10.58536127},
{"learn":[0.5436200196],"iteration":116,"passed_time":2.120209956,"remaining_time":10.56480688},
{"learn":[0.5435651437],"iteration":117,"passed_time":2.137997995,"remaining_time":10.54504096},
{"learn":[0.5434892967],"iteration":118,"passed_time":2.155619764,"remaining_time":10.52449649},
{"learn":[0.5434675423],"iteration":119,"passed_time":2.173894704,"remaining_time":10.50715774},
{"learn":[0.5434395681],"iteration":120,"passed_time":2.191193233,"remaining_time":10.48513125},
{"learn":[0.5433815794],"iteration":121,"passed_time":2.208590343,"remaining_time":10.46364933},
{"learn":[0.5433476597],"iteration":122,"passed_time":2.225930456,"remaining_time":10.44196645},
{"learn":[0.5432974474],"iteration":123,"passed_time":2.243207876,"remaining_time":10.42006239},
{"learn":[0.5432636165],"iteration":124,"passed_time":2.261327441,"remaining_time":10.40210623},
{"learn":[0.5432138927],"iteration":125,"passed_time":2.279834473,"remaining_time":10.3859126},
{"learn":[0.5431747711],"iteration":126,"passed_time":2.297483689,"remaining_time":10.36581223},
{"learn":[0.543141475],"iteration":127,"passed_time":2.314632006,"remaining_time":10.34351178},
{"learn":[0.5431054975],"iteration":128,"passed_time":2.332032175,"remaining_time":10.32240598},
{"learn":[0.5430586003],"iteration":129,"passed_time":2.349820719,"remaining_time":10.30306008},
{"learn":[0.5430054222],"iteration":130,"passed_time":2.367384726,"remaining_time":10.28276266},
{"learn":[0.5429523394],"iteration":131,"passed_time":2.384288264,"remaining_time":10.25966465},
{"learn":[0.5429094539],"iteration":132,"passed_time":2.401803533,"remaining_time":10.23926769},
{"learn":[0.5428782324],"iteration":133,"passed_time":2.419123291,"remaining_time":10.21808793},
{"learn":[0.5428561304],"iteration":134,"passed_time":2.436576243,"remaining_time":10.19752279},
{"learn":[0.5428162415],"iteration":135,"passed_time":2.453895136,"remaining_time":10.17644748},
{"learn":[0.5427772738],"iteration":136,"passed_time":2.470711599,"remaining_time":10.15336226},
{"learn":[0.5427388857],"iteration":137,"passed_time":2.487655152,"remaining_time":10.13088548},
{"learn":[0.5427107873],"iteration":138,"passed_time":2.50416495,"remaining_time":10.10673768},
{"learn":[0.5426769732],"iteration":139,"passed_time":2.520610635,"remaining_time":10.08244254},
{"learn":[0.5426462651],"iteration":140,"passed_time":2.53824628,"remaining_time":10.06297638},
{"learn":[0.5425910005],"iteration":141,"passed_time":2.555635177,"remaining_time":10.0425664},
{"learn":[0.5425738616],"iteration":142,"passed_time":2.573842896,"remaining_time":10.02538806},
{"learn":[0.5425387285],"iteration":143,"passed_time":2.592525722,"remaining_time":10.01002987},
{"learn":[0.5424948596],"iteration":144,"passed_time":2.609158555,"remaining_time":9.986779296},
{"learn":[0.542451944],"iteration":145,"passed_time":2.627561395,"remaining_time":9.970335704},
{"learn":[0.5424262896],"iteration":146,"passed_time":2.645112731,"remaining_time":9.950662178},
{"learn":[0.5424004734],"iteration":147,"passed_time":2.662064454,"remaining_time":9.928780938},
{"learn":[0.5423805524],"iteration":148,"passed_time":2.679962695,"remaining_time":9.910466074},
{"learn":[0.5423408823],"iteration":149,"passed_time":2.696593436,"remaining_time":9.887509265},
{"learn":[0.5423193597],"iteration":150,"passed_time":2.714610577,"remaining_time":9.869676864},
{"learn":[0.5423036185],"iteration":151,"passed_time":2.732820455,"remaining_time":9.852536904},
{"learn":[0.5422742337],"iteration":152,"passed_time":2.749682358,"remaining_time":9.830563724},
{"learn":[0.5422416692],"iteration":153,"passed_time":2.766813771,"remaining_time":9.809612459},
{"learn":[0.5422171411],"iteration":154,"passed_time":2.784389873,"remaining_time":9.79027407},
{"learn":[0.5421702775],"iteration":155,"passed_time":2.801589655,"remaining_time":9.769645976},
{"learn":[0.5421433583],"iteration":156,"passed_time":2.818735118,"remaining_time":9.748873688},
{"learn":[0.5421155568],"iteration":157,"passed_time":2.835981769,"remaining_time":9.728494424},
{"learn":[0.5420945357],"iteration":158,"passed_time":2.85331872,"remaining_time":9.708461807},
{"learn":[0.5420715873],"iteration":159,"passed_time":2.870882048,"remaining_time":9.689226913},
{"learn":[0.5420460522],"iteration":160,"passed_time":2.889474468,"remaining_time":9.673458001},
{"learn":[0.5420309788],"iteration":161,"passed_time":2.906786579,"remaining_time":9.653402343},
{"learn":[0.5420116517],"iteration":162,"passed_time":2.924607681,"remaining_time":9.635057206},
{"learn":[0.5419574153],"iteration":163,"passed_time":2.941437201,"remaining_time":9.613477681},
{"learn":[0.5419423021],"iteration":164,"passed_time":2.95875431,"remaining_time":9.593536701},
{"learn":[0.5418975243],"iteration":165,"passed_time":2.976916194,"remaining_time":9.576344866},
{"learn":[0.541868551],"iteration":166,"passed_time":2.994399463,"remaining_time":9.556975531},
{"learn":[0.5418442646],"iteration":167,"passed_time":3.011941959,"remaining_time":9.537816203},
{"learn":[0.5418232462],"iteration":168,"passed_time":3.029607642,"remaining_time":9.519063063},
{"learn":[0.5418015128],"iteration":169,"passed_time":3.048002215,"remaining_time":9.50259514},
{"learn":[0.5417854775],"iteration":170,"passed_time":3.065583376,"remaining_time":9.483588339},
{"learn":[0.541764071],"iteration":171,"passed_time":3.082437032,"remaining_time":9.462364843},
{"learn":[0.5417278759],"iteration":172,"passed_time":3.099568378,"remaining_time":9.442037775},
{"learn":[0.5416743243],"iteration":173,"passed_time":3.115809374,"remaining_time":9.419055922},
{"learn":[0.5416467577],"iteration":174,"passed_time":3.133787932,"remaining_time":9.401363797},
{"learn":[0.5416137758],"iteration":175,"passed_time":3.150637203,"remaining_time":9.380306218},
{"learn":[0.5415816695],"iteration":176,"passed_time":3.167640589,"remaining_time":9.359751571},
{"learn":[0.5415448601],"iteration":177,"passed_time":3.184757674,"remaining_time":9.339570257},
{"learn":[0.5415345502],"iteration":178,"passed_time":3.202139416,"remaining_time":9.320193497},
{"learn":[0.5415159919],"iteration":179,"passed_time":3.219790126,"remaining_time":9.301615919},
{"learn":[0.5414963418],"iteration":180,"passed_time":3.237287048,"remaining_time":9.282607612},
{"learn":[0.5414595475],"iteration":181,"passed_time":3.254157799,"remaining_time":9.261833735},
{"learn":[0.5414341905],"iteration":182,"passed_time":3.271823061,"remaining_time":9.243347119},
{"learn":[0.5413919862],"iteration":183,"passed_time":3.289306707,"remaining_time":9.224360113},
{"learn":[0.5413723003],"iteration":184,"passed_time":3.307185347,"remaining_time":9.206488938},
{"learn":[0.541348889],"iteration":185,"passed_time":3.324628256,"remaining_time":9.187413567},
{"learn":[0.5413276602],"iteration":186,"passed_time":3.34137174,"remaining_time":9.166436913},
{"learn":[0.5413048242],"iteration":187,"passed_time":3.357957673,"remaining_time":9.145076215},
{"learn":[0.5412724921],"iteration":188,"passed_time":3.374526804,"remaining_time":9.12372062},
{"learn":[0.5412549406],"iteration":189,"passed_time":3.392090509,"remaining_time":9.10508505},
{"learn":[0.5412196124],"iteration":190,"passed_time":3.408647966,"remaining_time":9.083779134},
{"learn":[0.5411770337],"iteration":191,"passed_time":3.425426832,"remaining_time":9.063108494},
{"learn":[0.5411358666],"iteration":192,"passed_time":3.441513646,"remaining_time":9.0406602},
{"learn":[0.5410997036],"iteration":193,"passed_time":3.45907793,"remaining_time":9.022131095},
{"learn":[0.5410737346],"iteration":194,"passed_time":3.477055002,"remaining_time":9.004680901},
{"learn":[0.5410529868],"iteration":195,"passed_time":3.494002746,"remaining_time":8.984578489},
{"learn":[0.5410262478],"iteration":196,"passed_time":3.511778459,"remaining_time":8.966622158},
{"learn":[0.5409972144],"iteration":197,"passed_time":3.528751226,"remaining_time":8.946631896},
{"learn":[0.5409533065],"iteration":198,"passed_time":3.546082936,"remaining_time":8.927575633},
{"learn":[0.5409299536],"iteration":199,"passed_time":3.563629721,"remaining_time":8.909074303},
{"learn":[0.5409038187],"iteration":200,"passed_time":3.58122618,"remaining_time":8.89070579},
{"learn":[0.5408834026],"iteration":201,"passed_time":3.598694777,"remaining_time":8.872029697},
{"learn":[0.5408710248],"iteration":202,"passed_time":3.615390652,"remaining_time":8.851473666},
{"learn":[0.5408464841],"iteration":203,"passed_time":3.631300279,"remaining_time":8.829043815},
{"learn":[0.5408279716],"iteration":204,"passed_time":3.647480226,"remaining_time":8.807330302},
{"learn":[0.5408147899],"iteration":205,"passed_time":3.664368992,"remaining_time":8.787370301},
{"learn":[0.540803263],"iteration":206,"passed_time":3.681860451,"remaining_time":8.768875373},
{"learn":[0.5407738966],"iteration":207,"passed_time":3.698600548,"remaining_time":8.748612835},
{"learn":[0.5407571577],"iteration":208,"passed_time":3.716375531,"remaining_time":8.730815244},
{"learn":[0.5407459419],"iteration":209,"passed_time":3.733231451,"remaining_time":8.710873385},
{"learn":[0.5407251397],"iteration":210,"passed_time":3.751666752,"remaining_time":8.69462105},
{"learn":[0.5406834783],"iteration":211,"passed_time":3.769601339,"remaining_time":8.677195536},
{"learn":[0.5406540033],"iteration":212,"passed_time":3.786312075,"remaining_time":8.656967045},
{"learn":[0.5406302951],"iteration":213,"passed_time":3.803005297,"remaining_time":8.636731656},
{"learn":[0.5405870438],"iteration":214,"passed_time":3.820568089,"remaining_time":8.618490806},
{"learn":[0.5405430816],"iteration":215,"passed_time":3.837913355,"remaining_time":8.599768814},
{"learn":[0.5405188943],"iteration":216,"passed_time":3.853961585,"remaining_time":8.578172561},
{"learn":[0.5404951071],"iteration":217,"passed_time":3.870721785,"remaining_time":8.558201378},
{"learn":[0.5404797662],"iteration":218,"passed_time":3.88747211,"remaining_time":8.538237831},
{"learn":[0.5404662837],"iteration":219,"passed_time":3.905658527,"remaining_time":8.521436787},
{"learn":[0.5404415377],"iteration":220,"passed_time":3.922089541,"remaining_time":8.500818508},
{"learn":[0.5404188664],"iteration":221,"passed_time":3.939512174,"remaining_time":8.48237306},
{"learn":[0.5403954989],"iteration":222,"passed_time":3.957612634,"remaining_time":8.465386666},
{"learn":[0.5403724503],"iteration":223,"passed_time":3.973660047,"remaining_time":8.4440276},
{"learn":[0.5403564334],"iteration":224,"passed_time":3.990909915,"remaining_time":8.425254265},
{"learn":[0.5403381302],"iteration":225,"passed_time":4.007487642,"remaining_time":8.405084701},
{"learn":[0.540313525],"iteration":226,"passed_time":4.025540748,"remaining_time":8.38802103},
{"learn":[0.5403009895],"iteration":227,"passed_time":4.044136712,"remaining_time":8.372072491},
{"learn":[0.54027744],"iteration":228,"passed_time":4.063240759,"remaining_time":8.357145842},
{"learn":[0.5402546389],"iteration":229,"passed_time":4.082001562,"remaining_time":8.341481453},
{"learn":[0.5402357475],"iteration":230,"passed_time":4.100860499,"remaining_time":8.325989498},
{"learn":[0.5402051756],"iteration":231,"passed_time":4.118403742,"remaining_time":8.307814446},
{"learn":[0.5401961465],"iteration":232,"passed_time":4.137321624,"remaining_time":8.292399993},
{"learn":[0.5401810202],"iteration":233,"passed_time":4.154922437,"remaining_time":8.274332717},
{"learn":[0.5401626453],"iteration":234,"passed_time":4.173200992,"remaining_time":8.257610474},
{"learn":[0.5401360374],"iteration":235,"passed_time":4.190893451,"remaining_time":8.239722717},
{"learn":[0.5401046469],"iteration":236,"passed_time":4.208260711,"remaining_time":8.221201305},
{"learn":[0.5400918605],"iteration":237,"passed_time":4.225686705,"remaining_time":8.202803604},
{"learn":[0.5400648115],"iteration":238,"passed_time":4.243809678,"remaining_time":8.185758416},
{"learn":[0.5400206342],"iteration":239,"passed_time":4.261318384,"remaining_time":8.167526903},
{"learn":[0.539988914],"iteration":240,"passed_time":4.278253104,"remaining_time":8.148208194},
{"learn":[0.5399660683],"iteration":241,"passed_time":4.296104429,"remaining_time":8.13064392},
{"learn":[0.5399467917],"iteration":242,"passed_time":4.31446389,"remaining_time":8.114032912},
{"learn":[0.5399320085],"iteration":243,"passed_time":4.333503294,"remaining_time":8.098678288},
{"learn":[0.5399143609],"iteration":244,"passed_time":4.351076405,"remaining_time":8.080570467},
{"learn":[0.5398765714],"iteration":245,"passed_time":4.369266262,"remaining_time":8.063605215},
{"learn":[0.539860594],"iteration":246,"passed_time":4.386960282,"remaining_time":8.045720678},
{"learn":[0.5398456849],"iteration":247,"passed_time":4.404814869,"remaining_time":8.028130326},
{"learn":[0.5398307296],"iteration":248,"passed_time":4.422658764,"remaining_time":8.010518484},
{"learn":[0.5398062848],"iteration":249,"passed_time":4.44023403,"remaining_time":7.992421254},
{"learn":[0.5397771711],"iteration":250,"passed_time":4.456860548,"remaining_time":7.97263102},
{"learn":[0.5397604608],"iteration":251,"passed_time":4.47416188,"remaining_time":7.954065565},
{"learn":[0.5397317471],"iteration":252,"passed_time":4.491898245,"remaining_time":7.936278717},
{"learn":[0.5397076086],"iteration":253,"passed_time":4.509601773,"remaining_time":7.918434609},
{"learn":[0.5396834256],"iteration":254,"passed_time":4.526645718,"remaining_time":7.899440566},
{"learn":[0.5396667692],"iteration":255,"passed_time":4.544532271,"remaining_time":7.881923158},
{"learn":[0.5396433576],"iteration":256,"passed_time":4.56300561,"remaining_time":7.865414339},
{"learn":[0.5396251738],"iteration":257,"passed_time":4.580762961,"remaining_time":7.847663677},
{"learn":[0.5396032291],"iteration":258,"passed_time":4.59778115,"remaining_time":7.828654391},
{"learn":[0.5395888656],"iteration":259,"passed_time":4.614299381,"remaining_time":7.808814337},
{"learn":[0.5395662101],"iteration":260,"passed_time":4.631732052,"remaining_time":7.790537819},
{"learn":[0.53956044],"iteration":261,"passed_time":4.648804334,"remaining_time":7.77166526},
{"learn":[0.5395382357],"iteration":262,"passed_time":4.666673623,"remaining_time":7.754130697},
{"learn":[0.5395121153],"iteration":263,"passed_time":4.684362892,"remaining_time":7.736296292},
{"learn":[0.5394868331],"iteration":264,"passed_time":4.702625453,"remaining_time":7.719404045},
{"learn":[0.5394561333],"iteration":265,"passed_time":4.720422246,"remaining_time":7.70174156},
{"learn":[0.5394386354],"iteration":266,"passed_time":4.738476188,"remaining_time":7.684495091},
{"learn":[0.5394172039],"iteration":267,"passed_time":4.757161513,"remaining_time":7.66826035},
{"learn":[0.5393959151],"iteration":268,"passed_time":4.774451761,"remaining_time":7.649772153},
{"learn":[0.5393651024],"iteration":269,"passed_time":4.793170686,"remaining_time":7.63356813},
{"learn":[0.5393496142],"iteration":270,"passed_time":4.811402335,"remaining_time":7.616574176},
{"learn":[0.5393324105],"iteration":271,"passed_time":4.829919885,"remaining_time":7.600020995},
{"learn":[0.5393248604],"iteration":272,"passed_time":4.850002082,"remaining_time":7.585900692},
{"learn":[0.5393103279],"iteration":273,"passed_time":4.869120148,"remaining_time":7.570237894},
{"learn":[0.5392872959],"iteration":274,"passed_time":4.88842081,"remaining_time":7.554832162},
{"learn":[0.5392590777],"iteration":275,"passed_time":4.907419189,"remaining_time":7.538933826},
{"learn":[0.5392362011],"iteration":276,"passed_time":4.926634252,"remaining_time":7.523344003},
{"learn":[0.5392180699],"iteration":277,"passed_time":4.945217291,"remaining_time":7.506768694},
{"learn":[0.5391977326],"iteration":278,"passed_time":4.962310271,"remaining_time":7.487930552},
{"learn":[0.5391677598],"iteration":279,"passed_time":4.980615785,"remaining_time":7.470923677},
{"learn":[0.5391515334],"iteration":280,"passed_time":4.999566366,"remaining_time":7.454869421},
{"learn":[0.539134953],"iteration":281,"passed_time":5.018055112,"remaining_time":7.43811006},
{"learn":[0.5391264056],"iteration":282,"passed_time":5.03732631,"remaining_time":7.422491419},
{"learn":[0.5391109454],"iteration":283,"passed_time":5.056513144,"remaining_time":7.406723479},
{"learn":[0.5390926818],"iteration":284,"passed_time":5.074996884,"remaining_time":7.389907744},
{"learn":[0.5390622861],"iteration":285,"passed_time":5.09357678,"remaining_time":7.373219535},
{"learn":[0.5390398516],"iteration":286,"passed_time":5.110968684,"remaining_time":7.354808594},
{"learn":[0.5390087546],"iteration":287,"passed_time":5.129454186,"remaining_time":7.337969183},
{"learn":[0.5389799639],"iteration":288,"passed_time":5.147339836,"remaining_time":7.320265303},
{"learn":[0.5389683594],"iteration":289,"passed_time":5.166718811,"remaining_time":7.304671423},
{"learn":[0.5389510533],"iteration":290,"passed_time":5.18550903,"remaining_time":7.288224032},
{"learn":[0.5389409001],"iteration":291,"passed_time":5.204152281,"remaining_time":7.271555242},
{"learn":[0.5389292959],"iteration":292,"passed_time":5.223530701,"remaining_time":7.255894182},
{"learn":[0.5389046523],"iteration":293,"passed_time":5.242753005,"remaining_time":7.239992244},
{"learn":[0.5388913597],"iteration":294,"passed_time":5.261677382,"remaining_time":7.223658779},
{"learn":[0.5388637696],"iteration":295,"passed_time":5.281064911,"remaining_time":7.207939946},
{"learn":[0.5388453838],"iteration":296,"passed_time":5.299516392,"remaining_time":7.190926282},
{"learn":[0.5388340308],"iteration":297,"passed_time":5.318548062,"remaining_time":7.174685641},
{"learn":[0.5388195493],"iteration":298,"passed_time":5.337502171,"remaining_time":7.158322309},
{"learn":[0.5388012582],"iteration":299,"passed_time":5.356145637,"remaining_time":7.141527516},
{"learn":[0.5387624696],"iteration":300,"passed_time":5.374817372,"remaining_time":7.124757911},
{"learn":[0.5387211976],"iteration":301,"passed_time":5.393966791,"remaining_time":7.108605241},
{"learn":[0.5386987912],"iteration":302,"passed_time":5.411829182,"remaining_time":7.090746487},
{"learn":[0.5386746134],"iteration":303,"passed_time":5.429267136,"remaining_time":7.072334823},
{"learn":[0.5386537841],"iteration":304,"passed_time":5.447380355,"remaining_time":7.054804066},
{"learn":[0.53863178],"iteration":305,"passed_time":5.466361101,"remaining_time":7.038386516},
{"learn":[0.5386071233],"iteration":306,"passed_time":5.484588773,"remaining_time":7.020988234},
{"learn":[0.5385935214],"iteration":307,"passed_time":5.504692285,"remaining_time":7.005972},
{"learn":[0.538566041],"iteration":308,"passed_time":5.523579387,"remaining_time":6.989383625},
{"learn":[0.5385406406],"iteration":309,"passed_time":5.542067378,"remaining_time":6.972278315},
{"learn":[0.5385295938],"iteration":310,"passed_time":5.561916428,"remaining_time":6.956866529},
{"learn":[0.538515045],"iteration":311,"passed_time":5.58089246,"remaining_time":6.940340623},
{"learn":[0.538499476],"iteration":312,"passed_time":5.600776337,"remaining_time":6.924921541},
{"learn":[0.5384932937],"iteration":313,"passed_time":5.619934878,"remaining_time":6.908582366},
{"learn":[0.5384763587],"iteration":314,"passed_time":5.638070445,"remaining_time":6.890974988},
{"learn":[0.5384539788],"iteration":315,"passed_time":5.655607824,"remaining_time":6.872637356},
{"learn":[0.5384355111],"iteration":316,"passed_time":5.675121627,"remaining_time":6.856692692},
{"learn":[0.5384067855],"iteration":317,"passed_time":5.692798393,"remaining_time":6.838518825},
{"learn":[0.5383878898],"iteration":318,"passed_time":5.711290358,"remaining_time":6.821321713},
{"learn":[0.5383712009],"iteration":319,"passed_time":5.729897456,"remaining_time":6.804253228},
{"learn":[0.5383604773],"iteration":320,"passed_time":5.749595253,"remaining_time":6.788462931},
{"learn":[0.5383440784],"iteration":321,"passed_time":5.767923902,"remaining_time":6.771041102},
{"learn":[0.5383218328],"iteration":322,"passed_time":5.785922284,"remaining_time":6.753228177},
{"learn":[0.5382946035],"iteration":323,"passed_time":5.805394734,"remaining_time":6.737124753},
{"learn":[0.5382860545],"iteration":324,"passed_time":5.825634513,"remaining_time":6.721885977},
{"learn":[0.5382694561],"iteration":325,"passed_time":5.844922392,"remaining_time":6.705524462},
{"learn":[0.5382523248],"iteration":326,"passed_time":5.864603195,"remaining_time":6.689593247},
{"learn":[0.5382271871],"iteration":327,"passed_time":5.885610412,"remaining_time":6.675143516},
{"learn":[0.5382144751],"iteration":328,"passed_time":5.904074559,"remaining_time":6.657786205},
{"learn":[0.5381979282],"iteration":329,"passed_time":5.922934809,"remaining_time":6.640866301},
{"learn":[0.5381709852],"iteration":330,"passed_time":5.941075469,"remaining_time":6.623132471},
{"learn":[0.5381610542],"iteration":331,"passed_time":5.96002804,"remaining_time":6.606296141},
{"learn":[0.5381488297],"iteration":332,"passed_time":5.97904925,"remaining_time":6.589522747},
{"learn":[0.5381232916],"iteration":333,"passed_time":5.996575333,"remaining_time":6.571097521},
{"learn":[0.5381040593],"iteration":334,"passed_time":6.015740479,"remaining_time":6.554463507},
{"learn":[0.538079788],"iteration":335,"passed_time":6.033605177,"remaining_time":6.536405608},
{"learn":[0.5380704041],"iteration":336,"passed_time":6.05276186,"remaining_time":6.51974052},
{"learn":[0.5380515996],"iteration":337,"passed_time":6.071087867,"remaining_time":6.502171029},
{"learn":[0.5380306684],"iteration":338,"passed_time":6.088898994,"remaining_time":6.484048782},
{"learn":[0.5380111335],"iteration":339,"passed_time":6.107145803,"remaining_time":6.466389674},
{"learn":[0.5379860242],"iteration":340,"passed_time":6.124714142,"remaining_time":6.448012836},
{"learn":[0.5379769591],"iteration":341,"passed_time":6.142810319,"remaining_time":6.430193258},
{"learn":[0.5379640074],"iteration":342,"passed_time":6.159937705,"remaining_time":6.411363733},
{"learn":[0.5379539234],"iteration":343,"passed_time":6.177222144,"remaining_time":6.392706637},
{"learn":[0.5379402227],"iteration":344,"passed_time":6.195657772,"remaining_time":6.375242055},
{"learn":[0.5379211178],"iteration":345,"passed_time":6.213530716,"remaining_time":6.357196166},
{"learn":[0.5378979572],"iteration":346,"passed_time":6.234067446,"remaining_time":6.341861119},
{"learn":[0.537876145],"iteration":347,"passed_time":6.251881259,"remaining_time":6.323741963},
{"learn":[0.5378613459],"iteration":348,"passed_time":6.270868382,"remaining_time":6.30680459},
{"learn":[0.5378455161],"iteration":349,"passed_time":6.288146601,"remaining_time":6.288146601},
{"learn":[0.5378262315],"iteration":350,"passed_time":6.307677372,"remaining_time":6.27173619},
{"learn":[0.5378209214],"iteration":351,"passed_time":6.325547023,"remaining_time":6.253665806},
{"learn":[0.5378015664],"iteration":352,"passed_time":6.343540038,"remaining_time":6.235717828},
{"learn":[0.5377756172],"iteration":353,"passed_time":6.36217343,"remaining_time":6.218395499},
{"learn":[0.5377588768],"iteration":354,"passed_time":6.381627323,"remaining_time":6.201863173},
{"learn":[0.5377474474],"iteration":355,"passed_time":6.399903932,"remaining_time":6.184176833},
{"learn":[0.5377388499],"iteration":356,"passed_time":6.418037192,"remaining_time":6.166349459},
{"learn":[0.5377254823],"iteration":357,"passed_time":6.435350662,"remaining_time":6.147737225},
{"learn":[0.5377145932],"iteration":358,"passed_time":6.453261196,"remaining_time":6.129699353},
{"learn":[0.537703208],"iteration":359,"passed_time":6.470448805,"remaining_time":6.110979427},
{"learn":[0.5376815903],"iteration":360,"passed_time":6.487124314,"remaining_time":6.091787098},
{"learn":[0.5376583052],"iteration":361,"passed_time":6.504230505,"remaining_time":6.073010803},
{"learn":[0.5376413512],"iteration":362,"passed_time":6.521187961,"remaining_time":6.054105628},
{"learn":[0.5376301428],"iteration":363,"passed_time":6.539632141,"remaining_time":6.036583515},
{"learn":[0.5376213946],"iteration":364,"passed_time":6.557836294,"remaining_time":6.018836051},
{"learn":[0.5376048814],"iteration":365,"passed_time":6.575663313,"remaining_time":6.000741931},
{"learn":[0.5375901961],"iteration":366,"passed_time":6.593181076,"remaining_time":5.98236866},
{"learn":[0.5375598674],"iteration":367,"passed_time":6.610983724,"remaining_time":5.964257056},
{"learn":[0.5375469707],"iteration":368,"passed_time":6.628459636,"remaining_time":5.945854037},
{"learn":[0.537521807],"iteration":369,"passed_time":6.64734524,"remaining_time":5.928713322},
{"learn":[0.5375034447],"iteration":370,"passed_time":6.663874497,"remaining_time":5.909473611},
{"learn":[0.5374778129],"iteration":371,"passed_time":6.681387609,"remaining_time":5.891115956},
{"learn":[0.5374706056],"iteration":372,"passed_time":6.698838265,"remaining_time":5.872708077},
{"learn":[0.5374202325],"iteration":373,"passed_time":6.716636659,"remaining_time":5.854608425},
{"learn":[0.5374061501],"iteration":374,"passed_time":6.734181379,"remaining_time":5.836290528},
{"learn":[0.5373861443],"iteration":375,"passed_time":6.749395908,"remaining_time":5.815968814},
{"learn":[0.5373534471],"iteration":376,"passed_time":6.767523794,"remaining_time":5.798170253},
{"learn":[0.5373403055],"iteration":377,"passed_time":6.78412103,"remaining_time":5.779066063},
{"learn":[0.53732824],"iteration":378,"passed_time":6.802622252,"remaining_time":5.761587712},
{"learn":[0.5373048816],"iteration":379,"passed_time":6.820580244,"remaining_time":5.743646521},
{"learn":[0.5372901313],"iteration":380,"passed_time":6.840134656,"remaining_time":5.727041877},
{"learn":[0.5372646289],"iteration":381,"passed_time":6.857116019,"remaining_time":5.708279827},
{"learn":[0.5372486096],"iteration":382,"passed_time":6.875422145,"remaining_time":5.690623551},
{"learn":[0.5372270595],"iteration":383,"passed_time":6.892557358,"remaining_time":5.672000326},
{"learn":[0.5372074296],"iteration":384,"passed_time":6.910772012,"remaining_time":5.65426801},
{"learn":[0.5371980551],"iteration":385,"passed_time":6.92980211,"remaining_time":5.637196535},
{"learn":[0.537182853],"iteration":386,"passed_time":6.947546603,"remaining_time":5.61907516},
{"learn":[0.5371739577],"iteration":387,"passed_time":6.965871516,"remaining_time":5.601422456},
{"learn":[0.5371487098],"iteration":388,"passed_time":6.984438252,"remaining_time":5.583959631},
{"learn":[0.5371332284],"iteration":389,"passed_time":7.002189018,"remaining_time":5.565842552},
{"learn":[0.5371199723],"iteration":390,"passed_time":7.020656227,"remaining_time":5.54829354},
{"learn":[0.5371090912],"iteration":391,"passed_time":7.037910109,"remaining_time":5.529786515},
{"learn":[0.5371004753],"iteration":392,"passed_time":7.05667407,"remaining_time":5.512465495},
{"learn":[0.5370783913],"iteration":393,"passed_time":7.073814584,"remaining_time":5.493876302},
{"learn":[0.5370624306],"iteration":394,"passed_time":7.090829691,"remaining_time":5.47519761},
{"learn":[0.5370500764],"iteration":395,"passed_time":7.109122623,"remaining_time":5.457508276},
{"learn":[0.5370255373],"iteration":396,"passed_time":7.125927446,"remaining_time":5.438680141},
{"learn":[0.5369999424],"iteration":397,"passed_time":7.141901044,"remaining_time":5.419231445},
{"learn":[0.5369925324],"iteration":398,"passed_time":7.158919668,"remaining_time":5.400588522},
{"learn":[0.5369804837],"iteration":399,"passed_time":7.17668715,"remaining_time":5.382515362},
{"learn":[0.536956335],"iteration":400,"passed_time":7.19373958,"remaining_time":5.36391056},
{"learn":[0.5369337445],"iteration":401,"passed_time":7.210678295,"remaining_time":5.345229184},
{"learn":[0.5369200637],"iteration":402,"passed_time":7.228369583,"remaining_time":5.327111082},
{"learn":[0.5369020443],"iteration":403,"passed_time":7.244780036,"remaining_time":5.30805666},
{"learn":[0.53687704],"iteration":404,"passed_time":7.263684879,"remaining_time":5.290832196},
{"learn":[0.5368626323],"iteration":405,"passed_time":7.281300187,"remaining_time":5.272665653},
{"learn":[0.5368425783],"iteration":406,"passed_time":7.299378997,"remaining_time":5.254835495},
{"learn":[0.5368186614],"iteration":407,"passed_time":7.316360178,"remaining_time":5.236218559},
{"learn":[0.5367781073],"iteration":408,"passed_time":7.334000616,"remaining_time":5.218078678},
{"learn":[0.5367645851],"iteration":409,"passed_time":7.350996339,"remaining_time":5.199485215},
{"learn":[0.5367571252],"iteration":410,"passed_time":7.368671468,"remaining_time":5.181377261},
{"learn":[0.5367438471],"iteration":411,"passed_time":7.387428155,"remaining_time":5.164027448},
{"learn":[0.5367283646],"iteration":412,"passed_time":7.40473287,"remaining_time":5.145661825},
{"learn":[0.5367091466],"iteration":413,"passed_time":7.422662724,"remaining_time":5.127733186},
{"learn":[0.5366811371],"iteration":414,"passed_time":7.440732865,"remaining_time":5.109900883},
{"learn":[0.5366653925],"iteration":415,"passed_time":7.458092908,"remaining_time":5.091582659},
{"learn":[0.5366523742],"iteration":416,"passed_time":7.475087914,"remaining_time":5.073021294},
{"learn":[0.5366327809],"iteration":417,"passed_time":7.492847013,"remaining_time":5.054982913},
{"learn":[0.5366222478],"iteration":418,"passed_time":7.510725426,"remaining_time":5.037025882},
{"learn":[0.5366073069],"iteration":419,"passed_time":7.528013744,"remaining_time":5.018675829},
{"learn":[0.5365882274],"iteration":420,"passed_time":7.544955294,"remaining_time":5.000101014},
{"learn":[0.5365762378],"iteration":421,"passed_time":7.563551082,"remaining_time":4.982623699},
{"learn":[0.5365587316],"iteration":422,"passed_time":7.582859723,"remaining_time":4.965607904},
{"learn":[0.5365465382],"iteration":423,"passed_time":7.60122421,"remaining_time":4.947966703},
{"learn":[0.5365401073],"iteration":424,"passed_time":7.619036659,"remaining_time":4.929964897},
{"learn":[0.5365328168],"iteration":425,"passed_time":7.637929315,"remaining_time":4.912658761},
{"learn":[0.5365166786],"iteration":426,"passed_time":7.657022297,"remaining_time":4.895473272},
{"learn":[0.5365080266],"iteration":427,"passed_time":7.674449307,"remaining_time":4.87722012},
{"learn":[0.5364921354],"iteration":428,"passed_time":7.694919806,"remaining_time":4.860893397},
{"learn":[0.5364818008],"iteration":429,"passed_time":7.714891435,"remaining_time":4.844234157},
{"learn":[0.5364709131],"iteration":430,"passed_time":7.73357595,"remaining_time":4.826756219},
{"learn":[0.5364549975],"iteration":431,"passed_time":7.752944333,"remaining_time":4.809696948},
{"learn":[0.5364405784],"iteration":432,"passed_time":7.77229576,"remaining_time":4.792616554},
{"learn":[0.5364203565],"iteration":433,"passed_time":7.790192104,"remaining_time":4.77463387},
{"learn":[0.5363974984],"iteration":434,"passed_time":7.808651874,"remaining_time":4.75699482},
{"learn":[0.5363876542],"iteration":435,"passed_time":7.827390427,"remaining_time":4.739520809},
{"learn":[0.5363694778],"iteration":436,"passed_time":7.847613608,"remaining_time":4.722934505},
{"learn":[0.5363536031],"iteration":437,"passed_time":7.865906519,"remaining_time":4.705176959},
{"learn":[0.536340658],"iteration":438,"passed_time":7.883830459,"remaining_time":4.687197608},
{"learn":[0.5363223882],"iteration":439,"passed_time":7.901473498,"remaining_time":4.669052522},
{"learn":[0.5362993357],"iteration":440,"passed_time":7.919716906,"remaining_time":4.65126231},
{"learn":[0.5362925016],"iteration":441,"passed_time":7.93974796,"remaining_time":4.634513515},
{"learn":[0.5362802971],"iteration":442,"passed_time":7.959037946,"remaining_time":4.617319982},
{"learn":[0.5362688826],"iteration":443,"passed_time":7.978687665,"remaining_time":4.600324419},
{"learn":[0.5362596219],"iteration":444,"passed_time":7.99933252,"remaining_time":4.583887174},
{"learn":[0.5362492813],"iteration":445,"passed_time":8.019761682,"remaining_time":4.567308222},
{"learn":[0.5362392086],"iteration":446,"passed_time":8.039664165,"remaining_time":4.550413946},
{"learn":[0.5362222914],"iteration":447,"passed_time":8.060577123,"remaining_time":4.534074631},
{"learn":[0.5362026752],"iteration":448,"passed_time":8.081668446,"remaining_time":4.517814654},
{"learn":[0.5361833063],"iteration":449,"passed_time":8.10287874,"remaining_time":4.5015993},
{"learn":[0.536160899],"iteration":450,"passed_time":8.124473624,"remaining_time":4.48557413},
{"learn":[0.5361360342],"iteration":451,"passed_time":8.145888949,"remaining_time":4.469425795},
{"learn":[0.5361233321],"iteration":452,"passed_time":8.166805808,"remaining_time":4.452982416},
{"learn":[0.536112674],"iteration":453,"passed_time":8.187133282,"remaining_time":4.436199972},
{"learn":[0.536098048],"iteration":454,"passed_time":8.207752958,"remaining_time":4.419559285},
{"learn":[0.5360854446],"iteration":455,"passed_time":8.227571441,"remaining_time":4.402472438},
{"learn":[0.5360697166],"iteration":456,"passed_time":8.247874894,"remaining_time":4.385631508},
{"learn":[0.536048835],"iteration":457,"passed_time":8.267059187,"remaining_time":4.368184112},
{"learn":[0.5360318287],"iteration":458,"passed_time":8.286830426,"remaining_time":4.351037326},
{"learn":[0.5360061884],"iteration":459,"passed_time":8.306027005,"remaining_time":4.333579307},
{"learn":[0.5359867586],"iteration":460,"passed_time":8.324257393,"remaining_time":4.315612835},
{"learn":[0.5359662001],"iteration":461,"passed_time":8.342945005,"remaining_time":4.29788076},
{"learn":[0.5359544143],"iteration":462,"passed_time":8.36231584,"remaining_time":4.280494285},
{"learn":[0.5359453972],"iteration":463,"passed_time":8.381699753,"remaining_time":4.263105909},
{"learn":[0.5359342838],"iteration":464,"passed_time":8.400759728,"remaining_time":4.245545239},
{"learn":[0.5359201568],"iteration":465,"passed_time":8.420195094,"remaining_time":4.228166635},
{"learn":[0.5359124669],"iteration":466,"passed_time":8.440492688,"remaining_time":4.211209414},
{"learn":[0.535886615],"iteration":467,"passed_time":8.459763273,"remaining_time":4.193728802},
{"learn":[0.5358569353],"iteration":468,"passed_time":8.479592902,"remaining_time":4.176515907},
{"learn":[0.5358505979],"iteration":469,"passed_time":8.498479449,"remaining_time":4.158830368},
{"learn":[0.5358322735],"iteration":470,"passed_time":8.517023369,"remaining_time":4.140973146},
{"learn":[0.5358246097],"iteration":471,"passed_time":8.538120901,"remaining_time":4.124346537},
{"learn":[0.5358139854],"iteration":472,"passed_time":8.558307252,"remaining_time":4.107263734},
{"learn":[0.5357959888],"iteration":473,"passed_time":8.577623418,"remaining_time":4.089752938},
{"learn":[0.5357809337],"iteration":474,"passed_time":8.595266545,"remaining_time":4.071442047},
{"learn":[0.5357642251],"iteration":475,"passed_time":8.628737338,"remaining_time":4.060582277},
{"learn":[0.5357458394],"iteration":476,"passed_time":8.646139423,"remaining_time":4.042115495},
{"learn":[0.5357372906],"iteration":477,"passed_time":8.664135042,"remaining_time":4.023928827},
{"learn":[0.5357152897],"iteration":478,"passed_time":8.683364686,"remaining_time":4.006312308},
{"learn":[0.5357087095],"iteration":479,"passed_time":8.702321131,"remaining_time":3.988563852},
{"learn":[0.5357003226],"iteration":480,"passed_time":8.720754582,"remaining_time":3.970572252},
{"learn":[0.5356831214],"iteration":481,"passed_time":8.738621968,"remaining_time":3.952322799},
{"learn":[0.5356695328],"iteration":482,"passed_time":8.757703305,"remaining_time":3.934620325},
{"learn":[0.5356617433],"iteration":483,"passed_time":8.77751819,"remaining_time":3.917239523},
{"learn":[0.5356468325],"iteration":484,"passed_time":8.797985566,"remaining_time":3.900137932},
{"learn":[0.5356302446],"iteration":485,"passed_time":8.817285518,"remaining_time":3.882508438},
{"learn":[0.5356180982],"iteration":486,"passed_time":8.838029243,"remaining_time":3.86550355},
{"learn":[0.5356058359],"iteration":487,"passed_time":8.857510373,"remaining_time":3.847934834},
{"learn":[0.5355957476],"iteration":488,"passed_time":8.876929983,"remaining_time":3.830331751},
{"learn":[0.5355708691],"iteration":489,"passed_time":8.896489891,"remaining_time":3.812781382},
{"learn":[0.5355543108],"iteration":490,"passed_time":8.914382202,"remaining_time":3.794512994},
{"learn":[0.5355376333],"iteration":491,"passed_time":8.932424898,"remaining_time":3.776309713},
{"learn":[0.5355246592],"iteration":492,"passed_time":8.9522237,"remaining_time":3.758844434},
{"learn":[0.5355044326],"iteration":493,"passed_time":8.981920444,"remaining_time":3.745497189},
{"learn":[0.5354965864],"iteration":494,"passed_time":9.003379513,"remaining_time":3.728672324},
{"learn":[0.5354925049],"iteration":495,"passed_time":9.023346682,"remaining_time":3.711215168},
{"learn":[0.5354819496],"iteration":496,"passed_time":9.043927026,"remaining_time":3.693998363},
{"learn":[0.5354677],"iteration":497,"passed_time":9.063596316,"remaining_time":3.676398505},
{"learn":[0.535450234],"iteration":498,"passed_time":9.081968661,"remaining_time":3.658267938},
{"learn":[0.5354407325],"iteration":499,"passed_time":9.102626994,"remaining_time":3.641050797},
{"learn":[0.5354254148],"iteration":500,"passed_time":9.122219486,"remaining_time":3.623396562},
{"learn":[0.5354113228],"iteration":501,"passed_time":9.141389675,"remaining_time":3.605568039},
{"learn":[0.5353900538],"iteration":502,"passed_time":9.160119455,"remaining_time":3.587561695},
{"learn":[0.5353813713],"iteration":503,"passed_time":9.178702719,"remaining_time":3.569495502},
{"learn":[0.5353582992],"iteration":504,"passed_time":9.197758358,"remaining_time":3.551609663},
{"learn":[0.5353423978],"iteration":505,"passed_time":9.215834667,"remaining_time":3.533343726},
{"learn":[0.5353307899],"iteration":506,"passed_time":9.234489927,"remaining_time":3.515298927},
{"learn":[0.535316251],"iteration":507,"passed_time":9.252687596,"remaining_time":3.497078776},
{"learn":[0.5353132944],"iteration":508,"passed_time":9.270060345,"remaining_time":3.478549167},
{"learn":[0.5352990535],"iteration":509,"passed_time":9.29040759,"remaining_time":3.461132239},
{"learn":[0.5352780305],"iteration":510,"passed_time":9.311393522,"remaining_time":3.44394007},
{"learn":[0.5352735005],"iteration":511,"passed_time":9.335012674,"remaining_time":3.427699966},
{"learn":[0.5352619205],"iteration":512,"passed_time":9.357248906,"remaining_time":3.410926989},
{"learn":[0.5352549563],"iteration":513,"passed_time":9.377599026,"remaining_time":3.393450231},
{"learn":[0.5352367044],"iteration":514,"passed_time":9.397529221,"remaining_time":3.375811468},
{"learn":[0.5352188445],"iteration":515,"passed_time":9.416762947,"remaining_time":3.357915469},
{"learn":[0.535198558],"iteration":516,"passed_time":9.437427337,"remaining_time":3.340520701},
{"learn":[0.5351888769],"iteration":517,"passed_time":9.457362261,"remaining_time":3.322857011},
{"learn":[0.535170735],"iteration":518,"passed_time":9.477593652,"remaining_time":3.30528796},
{"learn":[0.5351477283],"iteration":519,"passed_time":9.498392809,"remaining_time":3.287905203},
{"learn":[0.5351130193],"iteration":520,"passed_time":9.519632935,"remaining_time":3.270660836},
{"learn":[0.535098882],"iteration":521,"passed_time":9.541299577,"remaining_time":3.253546599},
{"learn":[0.5350930043],"iteration":522,"passed_time":9.563632103,"remaining_time":3.23664031},
{"learn":[0.5350863282],"iteration":523,"passed_time":9.586715615,"remaining_time":3.21996555},
{"learn":[0.5350746131],"iteration":524,"passed_time":9.609281638,"remaining_time":3.203093879},
{"learn":[0.53505346],"iteration":525,"passed_time":9.632452655,"remaining_time":3.186400688},
{"learn":[0.5350346675],"iteration":526,"passed_time":9.653354011,"remaining_time":3.168937844},
{"learn":[0.5350259955],"iteration":527,"passed_time":9.67419685,"remaining_time":3.151442913},
{"learn":[0.535017148],"iteration":528,"passed_time":9.695719145,"remaining_time":3.13415496},
{"learn":[0.5350037889],"iteration":529,"passed_time":9.715503154,"remaining_time":3.116293464},
{"learn":[0.5349854435],"iteration":530,"passed_time":9.734911508,"remaining_time":3.098305169},
{"learn":[0.5349537417],"iteration":531,"passed_time":9.753146522,"remaining_time":3.079941007},
{"learn":[0.5349235101],"iteration":532,"passed_time":9.772732757,"remaining_time":3.062000695},
{"learn":[0.5349191596],"iteration":533,"passed_time":9.790989136,"remaining_time":3.043640818},
{"learn":[0.5348863199],"iteration":534,"passed_time":9.809188288,"remaining_time":3.025263678},
{"learn":[0.5348717996],"iteration":535,"passed_time":9.827852264,"remaining_time":3.007029424},
{"learn":[0.534871225],"iteration":536,"passed_time":9.846963646,"remaining_time":2.988929375},
{"learn":[0.5348611019],"iteration":537,"passed_time":9.866463164,"remaining_time":2.97094244},
{"learn":[0.5348517374],"iteration":538,"passed_time":9.886705243,"remaining_time":2.953171696},
{"learn":[0.5348435091],"iteration":539,"passed_time":9.905423754,"remaining_time":2.934940371},
{"learn":[0.5348234398],"iteration":540,"passed_time":9.924400719,"remaining_time":2.916783206},
{"learn":[0.5348171007],"iteration":541,"passed_time":9.943980909,"remaining_time":2.898798863},
{"learn":[0.5348023802],"iteration":542,"passed_time":9.963073097,"remaining_time":2.880667544},
{"learn":[0.5347834213],"iteration":543,"passed_time":9.986217852,"remaining_time":2.863694825},
{"learn":[0.5347735936],"iteration":544,"passed_time":10.00957496,"remaining_time":2.846759851},
{"learn":[0.5347631841],"iteration":545,"passed_time":10.02959217,"remaining_time":2.82885933},
{"learn":[0.5347537745],"iteration":546,"passed_time":10.04918337,"remaining_time":2.810831911},
{"learn":[0.5347509102],"iteration":547,"passed_time":10.06877839,"remaining_time":2.792799845},
{"learn":[0.5347332394],"iteration":548,"passed_time":10.08957886,"remaining_time":2.775093638},
{"learn":[0.5347265891],"iteration":549,"passed_time":10.11080286,"remaining_time":2.75749169},
{"learn":[0.5347174846],"iteration":550,"passed_time":10.13295417,"remaining_time":2.740127353},
{"learn":[0.5347029302],"iteration":551,"passed_time":10.15348845,"remaining_time":2.72231212},
{"learn":[0.5346945683],"iteration":552,"passed_time":10.17365023,"remaining_time":2.704388036},
{"learn":[0.5346805173],"iteration":553,"passed_time":10.19639491,"remaining_time":2.687136565},
{"learn":[0.5346608567],"iteration":554,"passed_time":10.21729121,"remaining_time":2.669382389},
{"learn":[0.5346429249],"iteration":555,"passed_time":10.23754553,"remaining_time":2.65145064},
{"learn":[0.5346405428],"iteration":556,"passed_time":10.25915701,"remaining_time":2.633858981},
{"learn":[0.5346249714],"iteration":557,"passed_time":10.28029586,"remaining_time":2.616132637},
{"learn":[0.5346201555],"iteration":558,"passed_time":10.30163217,"remaining_time":2.598443893},
{"learn":[0.5346079842],"iteration":559,"passed_time":10.32382969,"remaining_time":2.580957422},
{"learn":[0.5345878293],"iteration":560,"passed_time":10.34608959,"remaining_time":2.563469613},
{"learn":[0.5345704221],"iteration":561,"passed_time":10.36887589,"remaining_time":2.54609408},
{"learn":[0.5345561738],"iteration":562,"passed_time":10.39002646,"remaining_time":2.528301288},
{"learn":[0.5345427873],"iteration":563,"passed_time":10.40962469,"remaining_time":2.510122265},
{"learn":[0.5345315526],"iteration":564,"passed_time":10.43003797,"remaining_time":2.492132965},
{"learn":[0.5345200697],"iteration":565,"passed_time":10.45278014,"remaining_time":2.474686464},
{"learn":[0.5345054534],"iteration":566,"passed_time":10.47375184,"remaining_time":2.456805987},
{"learn":[0.5344939484],"iteration":567,"passed_time":10.49478328,"remaining_time":2.43892851},
{"learn":[0.5344812224],"iteration":568,"passed_time":10.51608429,"remaining_time":2.421102007},
{"learn":[0.534469133],"iteration":569,"passed_time":10.53669927,"remaining_time":2.40310685},
{"learn":[0.5344510063],"iteration":570,"passed_time":10.55784668,"remaining_time":2.385222806},
{"learn":[0.5344394829],"iteration":571,"passed_time":10.57627213,"remaining_time":2.366718238},
{"learn":[0.5344313552],"iteration":572,"passed_time":10.59550032,"remaining_time":2.348391869},
{"learn":[0.5344268652],"iteration":573,"passed_time":10.61575856,"remaining_time":2.330288465},
{"learn":[0.5344115082],"iteration":574,"passed_time":10.63747652,"remaining_time":2.312494895},
{"learn":[0.5344021373],"iteration":575,"passed_time":10.65975851,"remaining_time":2.294809124},
{"learn":[0.5343999623],"iteration":576,"passed_time":10.67990527,"remaining_time":2.27665225},
{"learn":[0.5343794116],"iteration":577,"passed_time":10.70134029,"remaining_time":2.258760408},
{"learn":[0.5343533404],"iteration":578,"passed_time":10.72203444,"remaining_time":2.240701499},
{"learn":[0.5343389641],"iteration":579,"passed_time":10.74259433,"remaining_time":2.222605723},
{"learn":[0.5343290157],"iteration":580,"passed_time":10.76532744,"remaining_time":2.204946584},
{"learn":[0.5343253382],"iteration":581,"passed_time":10.78862029,"remaining_time":2.187383496},
{"learn":[0.5343121237],"iteration":582,"passed_time":10.80977162,"remaining_time":2.169370977},
{"learn":[0.53429567],"iteration":583,"passed_time":10.83478956,"remaining_time":2.152115735},
{"learn":[0.5342713621],"iteration":584,"passed_time":10.85908546,"remaining_time":2.134692014},
{"learn":[0.5342558415],"iteration":585,"passed_time":10.88224026,"remaining_time":2.117022848},
{"learn":[0.5342530211],"iteration":586,"passed_time":10.90423288,"remaining_time":2.09911127},
{"learn":[0.5342284469],"iteration":587,"passed_time":10.92344369,"remaining_time":2.080655941},
{"learn":[0.5342149035],"iteration":588,"passed_time":10.9434236,"remaining_time":2.062342987},
{"learn":[0.5342007696],"iteration":589,"passed_time":10.96290965,"remaining_time":2.043932307},
{"learn":[0.5341833422],"iteration":590,"passed_time":10.98131434,"remaining_time":2.02531855},
{"learn":[0.5341745889],"iteration":591,"passed_time":10.99941638,"remaining_time":2.006650285},
{"learn":[0.5341665621],"iteration":592,"passed_time":11.01794754,"remaining_time":1.988061361},
{"learn":[0.5341494802],"iteration":593,"passed_time":11.03624541,"remaining_time":1.969430999},
{"learn":[0.5341376459],"iteration":594,"passed_time":11.05498569,"remaining_time":1.950879828},
{"learn":[0.5341193442],"iteration":595,"passed_time":11.07338018,"remaining_time":1.932267682},
{"learn":[0.5341062102],"iteration":596,"passed_time":11.0919287,"remaining_time":1.913682841},
{"learn":[0.5340904485],"iteration":597,"passed_time":11.11073672,"remaining_time":1.895142384},
{"learn":[0.5340735427],"iteration":598,"passed_time":11.12979258,"remaining_time":1.876642822},
{"learn":[0.5340603599],"iteration":599,"passed_time":11.14943664,"remaining_time":1.858239439},
{"learn":[0.5340471842],"iteration":600,"passed_time":11.16813934,"remaining_time":1.839676863},
{"learn":[0.534040299],"iteration":601,"passed_time":11.18634341,"remaining_time":1.821032649},
{"learn":[0.5340275682],"iteration":602,"passed_time":11.20510177,"remaining_time":1.802479057},
{"learn":[0.5340208687],"iteration":603,"passed_time":11.22373369,"remaining_time":1.783904692},
{"learn":[0.5340108691],"iteration":604,"passed_time":11.24093806,"remaining_time":1.765105976},
{"learn":[0.5339912574],"iteration":605,"passed_time":11.25972661,"remaining_time":1.746558254},
{"learn":[0.5339747013],"iteration":606,"passed_time":11.27796957,"remaining_time":1.727926145},
{"learn":[0.5339637768],"iteration":607,"passed_time":11.29696106,"remaining_time":1.709408581},
{"learn":[0.5339547678],"iteration":608,"passed_time":11.31748482,"remaining_time":1.691118422},
{"learn":[0.53394302],"iteration":609,"passed_time":11.33891967,"remaining_time":1.67295536},
{"learn":[0.5339312251],"iteration":610,"passed_time":11.36023206,"remaining_time":1.654763754},
{"learn":[0.5339210062],"iteration":611,"passed_time":11.38138135,"remaining_time":1.636538495},
{"learn":[0.5338943127],"iteration":612,"passed_time":11.40232336,"remaining_time":1.618274277},
{"learn":[0.5338814613],"iteration":613,"passed_time":11.4221141,"remaining_time":1.599840086},
{"learn":[0.5338716949],"iteration":614,"passed_time":11.44263544,"remaining_time":1.581502459},
{"learn":[0.5338550096],"iteration":615,"passed_time":11.4625803,"remaining_time":1.563079132},
{"learn":[0.5338434975],"iteration":616,"passed_time":11.48206573,"remaining_time":1.544589069},
{"learn":[0.5338325848],"iteration":617,"passed_time":11.50194607,"remaining_time":1.526148184},
{"learn":[0.5338284209],"iteration":618,"passed_time":11.52243172,"remaining_time":1.507781857},
{"learn":[0.5338249496],"iteration":619,"passed_time":11.54313416,"remaining_time":1.489436666},
{"learn":[0.5338139728],"iteration":620,"passed_time":11.56413428,"remaining_time":1.471121752},
{"learn":[0.5337989194],"iteration":621,"passed_time":11.58237184,"remaining_time":1.452451774},
{"learn":[0.533788888],"iteration":622,"passed_time":11.60074861,"remaining_time":1.43380039},
{"learn":[0.5337805306],"iteration":623,"passed_time":11.62007257,"remaining_time":1.415265248},
{"learn":[0.5337699109],"iteration":624,"passed_time":11.63922119,"remaining_time":1.396706542},
{"learn":[0.5337656628],"iteration":625,"passed_time":11.65865991,"remaining_time":1.378180245},
{"learn":[0.5337518673],"iteration":626,"passed_time":11.67739659,"remaining_time":1.359569299},
{"learn":[0.5337414647],"iteration":627,"passed_time":11.69573379,"remaining_time":1.340912154},
{"learn":[0.5337318813],"iteration":628,"passed_time":11.71430512,"remaining_time":1.322282454},
{"learn":[0.5337232548],"iteration":629,"passed_time":11.733591,"remaining_time":1.303732334},
{"learn":[0.5337080029],"iteration":630,"passed_time":11.75322675,"remaining_time":1.28521814},
{"learn":[0.533692003],"iteration":631,"passed_time":11.77142824,"remaining_time":1.266546077},
{"learn":[0.5336756542],"iteration":632,"passed_time":11.78954013,"remaining_time":1.247866017},
{"learn":[0.5336638035],"iteration":633,"passed_time":11.80880918,"remaining_time":1.229308211},
{"learn":[0.5336553551],"iteration":634,"passed_time":11.82908349,"remaining_time":1.210851066},
{"learn":[0.533640908],"iteration":635,"passed_time":11.84916856,"remaining_time":1.192369163},
{"learn":[0.5336296158],"iteration":636,"passed_time":11.86845346,"remaining_time":1.173803089},
{"learn":[0.5336131086],"iteration":637,"passed_time":11.88710266,"remaining_time":1.155172985},
{"learn":[0.5335983064],"iteration":638,"passed_time":11.9066016,"remaining_time":1.13662394},
{"learn":[0.5335761057],"iteration":639,"passed_time":11.925906,"remaining_time":1.118053687},
{"learn":[0.5335659183],"iteration":640,"passed_time":11.944027,"remaining_time":1.09937222},
{"learn":[0.5335394769],"iteration":641,"passed_time":11.9627834,"remaining_time":1.080749902},
{"learn":[0.5335207647],"iteration":642,"passed_time":11.98038968,"remaining_time":1.062025212},
{"learn":[0.5334967717],"iteration":643,"passed_time":11.99982905,"remaining_time":1.043463395},
{"learn":[0.5334828927],"iteration":644,"passed_time":12.01885936,"remaining_time":1.024863976},
{"learn":[0.5334798188],"iteration":645,"passed_time":12.03768859,"remaining_time":1.006246414},
{"learn":[0.5334638679],"iteration":646,"passed_time":12.05597562,"remaining_time":0.9875837835},
{"learn":[0.5334510672],"iteration":647,"passed_time":12.07455273,"remaining_time":0.9689455895},
{"learn":[0.5334395373],"iteration":648,"passed_time":12.0931312,"remaining_time":0.9503076904},
{"learn":[0.5334247203],"iteration":649,"passed_time":12.11351918,"remaining_time":0.931809168},
{"learn":[0.5334179648],"iteration":650,"passed_time":12.13644813,"remaining_time":0.9134960958},
{"learn":[0.5334105882],"iteration":651,"passed_time":12.15938034,"remaining_time":0.8951691051},
{"learn":[0.5334015062],"iteration":652,"passed_time":12.17931539,"remaining_time":0.8766122871},
{"learn":[0.5333865482],"iteration":653,"passed_time":12.2000705,"remaining_time":0.8581089344},
{"learn":[0.5333718663],"iteration":654,"passed_time":12.22034428,"remaining_time":0.8395656376},
{"learn":[0.5333540207],"iteration":655,"passed_time":12.24062942,"remaining_time":0.8210178272},
{"learn":[0.5333395612],"iteration":656,"passed_time":12.26031011,"remaining_time":0.8024251668},
{"learn":[0.5333281376],"iteration":657,"passed_time":12.27948338,"remaining_time":0.7837968117},
{"learn":[0.5333138836],"iteration":658,"passed_time":12.29877644,"remaining_time":0.7651742548},
{"learn":[0.5333035091],"iteration":659,"passed_time":12.31831678,"remaining_time":0.7465646531},
{"learn":[0.5332820237],"iteration":660,"passed_time":12.33860006,"remaining_time":0.7279960702},
{"learn":[0.5332737631],"iteration":661,"passed_time":12.35827285,"remaining_time":0.7093872632},
{"learn":[0.5332611451],"iteration":662,"passed_time":12.37752943,"remaining_time":0.6907520196},
{"learn":[0.5332520599],"iteration":663,"passed_time":12.39706887,"remaining_time":0.6721302399},
{"learn":[0.5332371349],"iteration":664,"passed_time":12.41597918,"remaining_time":0.6534725885},
{"learn":[0.5332258704],"iteration":665,"passed_time":12.43487936,"remaining_time":0.6348136611},
{"learn":[0.5332148322],"iteration":666,"passed_time":12.46896359,"remaining_time":0.616905245},
{"learn":[0.5331959489],"iteration":667,"passed_time":12.51663905,"remaining_time":0.5995994752},
{"learn":[0.5331802096],"iteration":668,"passed_time":12.54800005,"remaining_time":0.5814469379},
{"learn":[0.5331709426],"iteration":669,"passed_time":12.58427269,"remaining_time":0.5634748967},
{"learn":[0.5331630598],"iteration":670,"passed_time":12.61527107,"remaining_time":0.5452203593},
{"learn":[0.5331367951],"iteration":671,"passed_time":12.65000372,"remaining_time":0.5270834882},
{"learn":[0.5331311278],"iteration":672,"passed_time":12.68396829,"remaining_time":0.5088664842},
{"learn":[0.5331251918],"iteration":673,"passed_time":12.72334179,"remaining_time":0.4908114042},
{"learn":[0.5331158333],"iteration":674,"passed_time":12.74886761,"remaining_time":0.4721802818},
{"learn":[0.5331013615],"iteration":675,"passed_time":12.76849363,"remaining_time":0.4533193003},
{"learn":[0.5330880173],"iteration":676,"passed_time":12.78799903,"remaining_time":0.4344519613},
{"learn":[0.5330833126],"iteration":677,"passed_time":12.80688185,"remaining_time":0.4155625378},
{"learn":[0.5330824759],"iteration":678,"passed_time":12.82716039,"remaining_time":0.3967163007},
{"learn":[0.533066207],"iteration":679,"passed_time":12.84726895,"remaining_time":0.3778608513},
{"learn":[0.5330380758],"iteration":680,"passed_time":12.86678926,"remaining_time":0.3589853098},
{"learn":[0.5330233502],"iteration":681,"passed_time":12.89475052,"remaining_time":0.340330659},
{"learn":[0.5330009151],"iteration":682,"passed_time":12.92231402,"remaining_time":0.3216388556},
{"learn":[0.5329915801],"iteration":683,"passed_time":12.94837802,"remaining_time":0.3028860355},
{"learn":[0.5329875546],"iteration":684,"passed_time":12.96907498,"remaining_time":0.2839943427},
{"learn":[0.532976885],"iteration":685,"passed_time":12.9883451,"remaining_time":0.2650682674},
{"learn":[0.5329660098],"iteration":686,"passed_time":13.00732002,"remaining_time":0.2461356045},
{"learn":[0.5329555445],"iteration":687,"passed_time":13.02712073,"remaining_time":0.2272172221},
{"learn":[0.5329515945],"iteration":688,"passed_time":13.045893,"remaining_time":0.2082798592},
{"learn":[0.5329446005],"iteration":689,"passed_time":13.06480431,"remaining_time":0.1893449899},
{"learn":[0.5329411348],"iteration":690,"passed_time":13.08279729,"remaining_time":0.1703982281},
{"learn":[0.5329249424],"iteration":691,"passed_time":13.10090654,"remaining_time":0.1514555669},
{"learn":[0.5329131627],"iteration":692,"passed_time":13.11893346,"remaining_time":0.1325144794},
{"learn":[0.5329020045],"iteration":693,"passed_time":13.13764895,"remaining_time":0.1135819794},
{"learn":[0.5328843356],"iteration":694,"passed_time":13.15593605,"remaining_time":0.09464702195},
{"learn":[0.5328708573],"iteration":695,"passed_time":13.17525304,"remaining_time":0.07571984508},
{"learn":[0.532854779],"iteration":696,"passed_time":13.19369288,"remaining_time":0.05678777423},
{"learn":[0.5328443339],"iteration":697,"passed_time":13.21227469,"remaining_time":0.0378575206},
{"learn":[0.5328349581],"iteration":698,"passed_time":13.2308947,"remaining_time":0.0189283186},
{"learn":[0.5328341314],"iteration":699,"passed_time":13.24992427,"remaining_time":0}
]}